conan_ue4cli/__init__.py
conan_ue4cli/descriptor.py
conan_ue4cli/main.py
conan_ue4cli/version.py
conan_ue4cli/commands/__init__.py
conan_ue4cli/commands/boilerplate.py
conan_ue4cli/commands/build.py
conan_ue4cli/commands/generate.py
conan_ue4cli/commands/precompute.py
conan_ue4cli/commands/sources.py
conan_ue4cli/commands/update.py
conan_ue4cli/common/CommandExecutor.py
conan_ue4cli/common/ConanTools.py
conan_ue4cli/common/DelegateManager.py
conan_ue4cli/common/ExecutableResolver.py
conan_ue4cli/common/LibraryResolver.py
conan_ue4cli/common/PackageBuilder.py
conan_ue4cli/common/PackageManagement.py
conan_ue4cli/common/PluginConfiguration.py
conan_ue4cli/common/ProfileManagement.py
conan_ue4cli/common/RecipeCache.py
conan_ue4cli/common/RecipeManagement.py
conan_ue4cli/common/Utility.py
conan_ue4cli/common/__init__.py
conan_ue4cli/data/boilerplate_templates/common/conanfile.py
conan_ue4cli/data/boilerplate_templates/v1/Template.Build.cs
conan_ue4cli/data/boilerplate_templates/v2/Template.Build.cs
conan_ue4cli/data/boilerplate_templates/v3/Template.Build.cs
conan_ue4cli/data/boilerplate_templates/v4/Template.Build.cs
conan_ue4cli/data/delegates/OpenSSL.py
conan_ue4cli/data/delegates/__default.py
conan_ue4cli/data/packages/libcxx/__init__.py
conan_ue4cli/data/packages/libcxx/conanfile.py
conan_ue4cli/data/packages/libcxx/libcxx.py
conan_ue4cli/data/packages/toolchain-wrapper/conanfile.py
conan_ue4cli/data/packages/toolchain-wrapper/wrappers/ClangInterposition.py
conan_ue4cli/data/packages/toolchain-wrapper/wrappers/clang++.py
conan_ue4cli/data/packages/toolchain-wrapper/wrappers/clang.py
conan_ue4cli/data/packages/ue4lib/__init__.py
conan_ue4cli/data/packages/ue4lib/conanfile.py
conan_ue4cli/data/packages/ue4lib/ue4lib.py
conan_ue4cli/data/packages/ue4util/__init__.py
conan_ue4cli/data/packages/ue4util/conanfile.py
conan_ue4cli/data/packages/ue4util/ue4util.py
conan_ue4cli/data/wrapper_template/conanfile.py
conan_ue4cli-0.0.38.dist-info/LICENSE
conan_ue4cli-0.0.38.dist-info/METADATA
conan_ue4cli-0.0.38.dist-info/WHEEL
conan_ue4cli-0.0.38.dist-info/entry_points.txt
conan_ue4cli-0.0.38.dist-info/top_level.txt
conan_ue4cli-0.0.38.dist-info/RECORD
