Metadata-Version: 2.1
Name: conan-ue4cli
Version: 0.0.38
Summary: Integrate third-party libraries into the Unreal Engine with Conan
Home-page: http://github.com/adamrehn/conan-ue4cli
Author: Adam Rehn
Author-email: adam@adamrehn.com
License: MIT
Keywords: epic unreal engine
Platform: UNKNOWN
Classifier: License :: OSI Approved :: MIT License
Classifier: Programming Language :: Python :: 3.5
Classifier: Programming Language :: Python :: 3.6
Classifier: Programming Language :: Python :: 3.7
Classifier: Topic :: Software Development :: Build Tools
Classifier: Environment :: Console
Requires-Python: >=3.5
Requires-Dist: conan (>=1.7.4)
Requires-Dist: setuptools
Requires-Dist: ue4cli (>=0.0.49)
Requires-Dist: wheel
